pro_gan_pytorch/CustomLayers.py
pro_gan_pytorch/DataTools.py
pro_gan_pytorch/PRO_GAN.py
pro_gan_pytorch/Progan_Losses.py
pro_gan_pytorch/SGAN.py
pro_gan_pytorch/__init__.py
pro_gan_pytorch/big_gan.py
pro_gan_pytorch/dataloaders.py
pro_gan_pytorch/dcgan_models.py
pro_gan_pytorch/dcgan_train.py
pro_gan_pytorch/gen.py
pro_gan_pytorch/metric/fid.py
pro_gan_pytorch/metric/inception.py
pro_gan_pytorch/metrics.py
pro_gan_pytorch/prod_train_progan.py
pro_gan_pytorch/remap.py
pro_gan_pytorch/sgan_loss.py
pro_gan_pytorch/sgan_train.py
pro_gan_pytorch/train.py
pro_gan_pytorch/utils/feature_extraction.py
pro_gan_pytorch/utils/gan.py
pro_gan_pytorch/utils/similarity_matrix.py
pro_gan_pytorch/wgan.py
pro_gan_pytorch/wgan_loss.py
pro_gan_pytorch-0.1.1.dist-info/entry_points.txt
pro_gan_pytorch-0.1.1.dist-info/WHEEL
pro_gan_pytorch-0.1.1.dist-info/METADATA
pro_gan_pytorch-0.1.1.dist-info/RECORD
