Metadata-Version: 2.1
Name: pro-gan-pytorch
Version: 0.1.1
Summary: various GANS training package
License: Apache-2.0
Author: Sindhura
Author-email: sindhura.k@fractal.ai
Requires-Python: ==3.6.9
Classifier: License :: OSI Approved :: Apache Software License
Classifier: Programming Language :: Python :: 3
Requires-Dist: PyYAML (==5.1.2)
Requires-Dist: albumentations (>=0.4.2,<0.5.0)
Requires-Dist: easydict (>=1.9,<2.0)
Requires-Dist: imageio (>=2.6,<3.0)
Requires-Dist: opencv-python (>=4.1,<5.0)
Requires-Dist: pandas (==0.25.2)
Requires-Dist: scikit-image (==0.16.2)
Requires-Dist: torch (==1.3.0)
Requires-Dist: torchnet (>=0.0.4,<0.0.5)
Requires-Dist: torchvision (==0.4.1)
Requires-Dist: tqdm (==4.36.1)
Requires-Dist: urllib3 (==1.25.6)
